ip_prefix_search.py
report2idea.py
nemea_pycommon-1.4.3.dist-info/DESCRIPTION.rst
nemea_pycommon-1.4.3.dist-info/METADATA
nemea_pycommon-1.4.3.dist-info/RECORD
nemea_pycommon-1.4.3.dist-info/WHEEL
nemea_pycommon-1.4.3.dist-info/metadata.json
nemea_pycommon-1.4.3.dist-info/top_level.txt
reporter_config/AddressGroup.py
reporter_config/Config.py
reporter_config/Parser.py
reporter_config/Rule.py
reporter_config/__init__.py
reporter_config/__main__.py
reporter_config/actions/Action.py
reporter_config/actions/Drop.py
reporter_config/actions/Email.py
reporter_config/actions/File.py
reporter_config/actions/Mark.py
reporter_config/actions/Mongo.py
reporter_config/actions/Trap.py
reporter_config/actions/Warden.py
reporter_config/actions/__init__.py
