Metadata-Version: 2.0
Name: nemea-pycommon
Version: 1.4.3
Summary: Common Python modules and methods of the NEMEA system.
Home-page: https://github.com/CESNET/Nemea-Framework
Author: Vaclav Bartos, CESNET
Author-email: bartos@cesnet.cz
Maintainer: Tomas Cejka
Maintainer-email: cejkat@cesnet.cz
License: BSD
Platform: any
Classifier: Development Status :: 4 - Beta
Classifier: License :: OSI Approved :: GNU General Public License v3 (GPLv3)
Classifier: Operating System :: POSIX
Classifier: Programming Language :: C
Classifier: Programming Language :: Python
Classifier: Programming Language :: Python :: 2
Classifier: Programming Language :: Python :: 3
Classifier: Topic :: Software Development :: Libraries
Classifier: Topic :: System :: Networking :: Monitoring
Requires-Dist: pynspect
Requires-Dist: idea-format
Requires-Dist: PyYAML
Requires-Dist: ply
Requires-Dist: jinja2
